citus/__init__.py
citus/__main__.py
citus/app.py
citus/blueprints.py
citus/cli.py
citus/config.py
citus/ctx.py
citus/debughelpers.py
citus/globals.py
citus/helpers.py
citus/logging.py
citus/py.typed
citus/scaffold.py
citus/sessions.py
citus/signals.py
citus/templating.py
citus/testing.py
citus/typing.py
citus/views.py
citus/wrappers.py
citus/json/__init__.py
citus/json/tag.py
citus/steroids/NoApp
citus/steroids/NoApp.cpp
citus/steroids/__init__.py
citus/steroids/currentdateandtime
citus/steroids/currentdateandtime.cpp
Citus-0.0.3.dist-info/LICENSE
Citus-0.0.3.dist-info/METADATA
Citus-0.0.3.dist-info/WHEEL
Citus-0.0.3.dist-info/entry_points.txt
Citus-0.0.3.dist-info/top_level.txt
Citus-0.0.3.dist-info/RECORD
