Metadata-Version: 2.1
Name: Citus
Version: 0.0.3
Summary: Ultrafast web framework  focusing on composing Web APIs all the more rapidly and with needless baggage.
Home-page: https://citus.rtfd.io
Author: Gerrishon Sirere
Author-email: secretum.inc@pm.me
Maintainer: Secretum Inc.
Maintainer-email: secretum.inc@pm.me
License: MIT
Project-URL: Donate, https://tinyurl.com/ygaj5fwj
Project-URL: Documentation, https://citus.rtfd.io
Project-URL: Changes, https://citus.rtfd.io/changes/
Project-URL: Source Code, https://github.com/secretum-inc/citus
Project-URL: Issue Tracker, https://github.com/secretum-inc/citus/issues/
Project-URL: Twitter, https://twitter.com/gerrishon_s
Project-URL: Chat, https://groups.google.com/forum/#!forum/secretum
Platform: UNKNOWN
Classifier: Development Status :: 5 - Production/Stable
Classifier: Environment :: Web Environment
Classifier: Intended Audience :: Developers
Classifier: License :: OSI Approved :: MIT License
Classifier: Operating System :: OS Independent
Classifier: Programming Language :: Python
Classifier: Topic :: Internet :: WWW/HTTP :: Dynamic Content
Classifier: Topic :: Internet :: WWW/HTTP :: WSGI
Classifier: Topic :: Internet :: WWW/HTTP :: WSGI :: Application
Classifier: Topic :: Software Development :: Libraries :: Application Frameworks
Requires-Python: >=3.8
License-File: LICENSE
Requires-Dist: Jinja2 (>=3.0)
Requires-Dist: Werkzeug (>=2.0)
Requires-Dist: itsdangerous (>=2.0)
Requires-Dist: quo (>=2022.1.6)
Provides-Extra: async
Requires-Dist: asgiref (>=3.2) ; extra == 'async'
Provides-Extra: dotenv
Requires-Dist: python-dotenv ; extra == 'dotenv'
